LICENSE
setup.py
gridly_api/__init__.py
gridly_api/gridly_api.py
gridly_api.egg-info/PKG-INFO
gridly_api.egg-info/SOURCES.txt
gridly_api.egg-info/dependency_links.txt
gridly_api.egg-info/requires.txt
gridly_api.egg-info/top_level.txt